IslandSheds/__init__.py
IslandSheds/downloader.py
IslandSheds-0.0.29.dist-info/LICENSE.txt
IslandSheds-0.0.29.dist-info/METADATA
IslandSheds-0.0.29.dist-info/WHEEL
IslandSheds-0.0.29.dist-info/entry_points.txt
IslandSheds-0.0.29.dist-info/top_level.txt
IslandSheds-0.0.29.dist-info/RECORD
